simbricks/runtime/__init__.py
simbricks/runtime/command_executor.py
simbricks/runtime/output.py
simbricks/runtime/runs/__init__.py
simbricks/runtime/runs/base.py
simbricks/runtime/runs/local.py
simbricks/runtime/simulation_executor.py
simbricks_runtime-0.3.6.dist-info/METADATA
simbricks_runtime-0.3.6.dist-info/WHEEL
simbricks_runtime-0.3.6.dist-info/RECORD
