Metadata-Version: 2.3
Name: simbricks-runtime
Version: 0.3.6
Summary: simbricks runtime lib required to simulate your virtual prototypes
Author: Team SimBricks
Author-email: team@simbricks.io
Classifier: Programming Language :: Python :: 2
Classifier: Programming Language :: Python :: 2.7
Classifier: Programming Language :: Python :: 3
Classifier: Programming Language :: Python :: 3.4
Classifier: Programming Language :: Python :: 3.5
Classifier: Programming Language :: Python :: 3.6
Classifier: Programming Language :: Python :: 3.7
Classifier: Programming Language :: Python :: 3.8
Classifier: Programming Language :: Python :: 3.9
Classifier: Programming Language :: Python :: 3.10
Classifier: Programming Language :: Python :: 3.11
Classifier: Programming Language :: Python :: 3.12
Classifier: Programming Language :: Python :: 3.13
Requires-Dist: pytype (==2024.10.11)
Requires-Dist: simbricks-orchestration (>=0.3.6)
Requires-Dist: simbricks-utils (>=0.3.2)
Project-URL: Homepage, https://www.simbricks.io/
